rxio/__init__.py
rxio/_typing.py
rxio/core.py
rxio/utils.py
rxio-0.1.4.dist-info/LICENSE
rxio-0.1.4.dist-info/WHEEL
rxio-0.1.4.dist-info/METADATA
rxio-0.1.4.dist-info/RECORD
