Metadata-Version: 2.1
Name: rxio
Version: 0.1.4
Summary: Flexible, predictable, async reactive programming in modern Python
Home-page: https://github.com/jorenham/rxio
License: MIT
Author: Joren Hammudoglu
Author-email: jhammudoglu@gmail.com
Requires-Python: >=3.9,<4.0
Classifier: License :: OSI Approved :: MIT License
Classifier: Programming Language :: Python :: 3
Classifier: Programming Language :: Python :: 3.10
Classifier: Programming Language :: Python :: 3.9
Requires-Dist: typing-extensions (>=4.3,<5.0); python_version < "3.10"
Project-URL: Repository, https://github.com/jorenham/rxio
